polars_rpsl-0.1.4.dist-info/METADATA
polars_rpsl-0.1.4.dist-info/WHEEL
polars_rpsl-0.1.4.dist-info/licenses/LICENSE
polars_rpsl/__init__.py
polars_rpsl/_rpsl_reader.cpython-39-x86_64-linux-gnu.so
polars_rpsl-0.1.4.dist-info/RECORD
