Metadata-Version: 2.4
Name: polars-rpsl
Version: 0.1.4
Classifier: Development Status :: 4 - Beta
Classifier: Intended Audience :: Developers
Classifier: Intended Audience :: Science/Research
Classifier: License :: OSI Approved :: MIT License
Classifier: Programming Language :: Python :: 3
Classifier: Programming Language :: Python :: 3.9
Classifier: Programming Language :: Python :: 3.10
Classifier: Programming Language :: Python :: 3.11
Classifier: Programming Language :: Python :: 3.12
Classifier: Programming Language :: Python :: 3.13
Classifier: Programming Language :: Rust
Classifier: Topic :: Internet
Classifier: Topic :: Software Development :: Libraries :: Python Modules
Classifier: Typing :: Typed
Requires-Dist: polars>=1.0
Requires-Dist: pyarrow>=15.0
License-File: LICENSE
Summary: Fast RPSL parser with Polars DataFrame output
Author: Ragnar Dahlén
License-Expression: MIT
Requires-Python: >=3.9
Project-URL: Homepage, https://github.com/ragnard/rpsl-reader
Project-URL: Repository, https://github.com/ragnard/rpsl-reader.git
